hangups/__init__.py
hangups/auth.py
hangups/channel.py
hangups/client.py
hangups/conversation.py
hangups/conversation_event.py
hangups/event.py
hangups/exceptions.py
hangups/hangouts_pb2.py
hangups/http_utils.py
hangups/message_parser.py
hangups/parsers.py
hangups/pblite.py
hangups/user.py
hangups/version.py
hangups/ui/__init__.py
hangups/ui/__main__.py
hangups/ui/emoticon.py
hangups/ui/notifier.py
hangups/ui/utils.py
tulir_hangups-0.4.12.dist-info/LICENSE
tulir_hangups-0.4.12.dist-info/METADATA
tulir_hangups-0.4.12.dist-info/WHEEL
tulir_hangups-0.4.12.dist-info/entry_points.txt
tulir_hangups-0.4.12.dist-info/top_level.txt
tulir_hangups-0.4.12.dist-info/RECORD
