Metadata-Version: 2.1
Name: tulir-hangups
Version: 0.4.12
Summary: UNKNOWN
Home-page: https://github.com/tulir/hangups
Author: Tulir Asokan
Author-email: tulir@maunium.net
License: MIT
Platform: UNKNOWN
Classifier: Development Status :: 3 - Alpha
Classifier: Intended Audience :: Developers
Classifier: Intended Audience :: End Users/Desktop
Classifier: Natural Language :: English
Classifier: License :: OSI Approved :: MIT License
Classifier: Programming Language :: Python :: 3 :: Only
Classifier: Programming Language :: Python :: 3.5
Classifier: Programming Language :: Python :: 3.6
Classifier: Topic :: Communications :: Chat
Classifier: Environment :: Console :: Curses
Requires-Dist: ConfigArgParse (==0.11.0)
Requires-Dist: aiohttp (<4,>=3.3)
Requires-Dist: async-timeout (<4,>=2)
Requires-Dist: appdirs (<1.5,>=1.4)
Requires-Dist: readlike (==0.1.2)
Requires-Dist: requests (<3,>=2.6.0)
Requires-Dist: ReParser (==1.4.3)
Requires-Dist: protobuf (<3.14,>=3.1.0)
Requires-Dist: urwid (==1.3.1)
Requires-Dist: MechanicalSoup (==0.6.0)
